open_prime_rando/__init__.py
open_prime_rando/__main__.py
open_prime_rando/cli.py
open_prime_rando/dynamic_schema.py
open_prime_rando/echoes_patcher.py
open_prime_rando/p1r_patcher.py
open_prime_rando/patcher_editor.py
open_prime_rando/py.typed
open_prime_rando/unique_area_name.py
open_prime_rando/validator_with_default.py
open_prime_rando/version.py
open_prime_rando/__pyinstaller/__init__.py
open_prime_rando/__pyinstaller/hook-open_prime_rando.py
open_prime_rando/dol_patching/__init__.py
open_prime_rando/dol_patching/all_prime_dol_patches.py
open_prime_rando/dol_patching/dol_version.py
open_prime_rando/dol_patching/corruption/__init__.py
open_prime_rando/dol_patching/corruption/dol_patches.py
open_prime_rando/dol_patching/corruption/dol_versions.py
open_prime_rando/dol_patching/echoes/__init__.py
open_prime_rando/dol_patching/echoes/beam_configuration.py
open_prime_rando/dol_patching/echoes/dol_patcher.py
open_prime_rando/dol_patching/echoes/dol_patches.py
open_prime_rando/dol_patching/echoes/dol_versions.py
open_prime_rando/dol_patching/echoes/user_preferences.py
open_prime_rando/dol_patching/prime1/__init__.py
open_prime_rando/dol_patching/prime1/dol_patches.py
open_prime_rando/dol_patching/prime1/dol_versions.py
open_prime_rando/echoes/schema.json
open_prime_rando/echoes/vulnerabilities.py
open_prime_rando/echoes/asset_ids/__init__.py
open_prime_rando/echoes/asset_ids/agon_wastes.py
open_prime_rando/echoes/asset_ids/great_temple.py
open_prime_rando/echoes/asset_ids/sanctuary_fortress.py
open_prime_rando/echoes/asset_ids/temple_grounds.py
open_prime_rando/echoes/asset_ids/torvus_bog.py
open_prime_rando/echoes/asset_ids/world.py
open_prime_rando/echoes/custom_assets/__init__.py
open_prime_rando/echoes/custom_assets/doors/custom_door_lock_boost_ball.TXTR
open_prime_rando/echoes/custom_assets/doors/custom_door_lock_boost_ball_emissive.TXTR
open_prime_rando/echoes/custom_assets/doors/custom_door_lock_cannon_ball.TXTR
open_prime_rando-0.15.1.dist-info/LICENSE
open_prime_rando-0.15.1.dist-info/METADATA
open_prime_rando-0.15.1.dist-info/WHEEL
open_prime_rando-0.15.1.dist-info/entry_points.txt
open_prime_rando-0.15.1.dist-info/top_level.txt
open_prime_rando-0.15.1.dist-info/RECORD
