Metadata-Version: 2.1
Name: open-prime-rando
Version: 0.15.1
Summary: An open source randomizer patcher for Metroid Prime 2 and 3.
Author: Henrique Gemignani
Project-URL: Homepage, https://github.com/randovania/open-prime-rando
Classifier: License :: OSI Approved :: GNU General Public License v3 (GPLv3)
Classifier: Development Status :: 3 - Alpha
Classifier: Intended Audience :: Developers
Classifier: Programming Language :: Python :: 3.10
Classifier: Programming Language :: Python :: 3.11
Classifier: Programming Language :: Python :: 3.12
Classifier: Programming Language :: Python :: 3.13
Requires-Python: >=3.10
License-File: LICENSE
Requires-Dist: retro-data-structures >=0.28.0
Requires-Dist: jsonschema >=4.0.0
Requires-Dist: ppc-asm
Requires-Dist: py-randomprime
Provides-Extra: test
Requires-Dist: pytest ; extra == 'test'
Requires-Dist: pytest-cov ; extra == 'test'
Requires-Dist: pytest-mock ; extra == 'test'
Requires-Dist: pytest-xdist ; extra == 'test'
Requires-Dist: pre-commit ; extra == 'test'
